LICENSE
README.md
pyproject.toml
setup.cfg
setup.py
dagcheck/__init__.py
dagcheck/api.py
dagcheck/base.py
dagcheck/execution.py
dagcheck.egg-info/PKG-INFO
dagcheck.egg-info/SOURCES.txt
dagcheck.egg-info/dependency_links.txt
dagcheck.egg-info/requires.txt
dagcheck.egg-info/top_level.txt
dagcheck/test/__init__.py
dagcheck/test/dagcheck_base_internals_test.py
dagcheck/test/dagcheck_execution_test.py
dagcheck/test/dagcheck_larger_dag_samples_test.py
dagcheck/test/dagcheck_simple_api_test.py
dagcheck/test/dagcheck_test_example_dags_utils.py